{
  "dados": [
    {
      "id": 74317,
      "uri": "https://dadosabertos.camara.leg.br/api/v2/deputados/74317",
      "nome": "JÚLIO CESAR",
      "siglaPartido": "PSD",
      "uriPartido": "https://dadosabertos.camara.leg.br/api/v2/partidos/36834",
      "siglaUf": "PI",
      "idLegislatura": 55,
      "urlFoto": "http://www.camara.leg.br/internet/deputado/bandep/74317.jpg"
    },
    {
      "id": 73586,
      "uri": "https://dadosabertos.camara.leg.br/api/v2/deputados/73586",
      "nome": "JÚLIO DELGADO",
      "siglaPartido": "PSB",
      "uriPartido": "https://dadosabertos.camara.leg.br/api/v2/partidos/36832",
      "siglaUf": "MG",
      "idLegislatura": 55,
      "urlFoto": "http://www.camara.leg.br/internet/deputado/bandep/73586.jpg"
    },
    {
      "id": 74253,
      "uri": "https://dadosabertos.camara.leg.br/api/v2/deputados/74253",
      "nome": "JULIO LOPES",
      "siglaPartido": "PP",
      "uriPartido": "https://dadosabertos.camara.leg.br/api/v2/partidos/36809",
      "siglaUf": "RJ",
      "idLegislatura": 55,
      "urlFoto": "http://www.camara.leg.br/internet/deputado/bandep/74253.jpg"
    },
    {
      "id": 178885,
      "uri": "https://dadosabertos.camara.leg.br/api/v2/deputados/178885",
      "nome": "JUNIOR MARRECA",
      "siglaPartido": "PEN",
      "uriPartido": "https://dadosabertos.camara.leg.br/api/v2/partidos/36761",
      "siglaUf": "MA",
      "idLegislatura": 55,
      "urlFoto": "http://www.camara.leg.br/internet/deputado/bandep/178885.jpg"
    },
    {
      "id": 178886,
      "uri": "https://dadosabertos.camara.leg.br/api/v2/deputados/178886",
      "nome": "JUSCELINO FILHO",
      "siglaPartido": "DEM",
      "uriPartido": "https://dadosabertos.camara.leg.br/api/v2/partidos/36769",
      "siglaUf": "MA",
      "idLegislatura": 55,
      "urlFoto": "http://www.camara.leg.br/internet/deputado/bandep/178886.jpg"
    },
    {
      "id": 74570,
      "uri": "https://dadosabertos.camara.leg.br/api/v2/deputados/74570",
      "nome": "JUTAHY JUNIOR",
      "siglaPartido": "PSDB",
      "uriPartido": "https://dadosabertos.camara.leg.br/api/v2/partidos/36835",
      "siglaUf": "BA",
      "idLegislatura": 55,
      "urlFoto": "http://www.camara.leg.br/internet/deputado/bandep/74570.jpg"
    },
    {
      "id": 178918,
      "uri": "https://dadosabertos.camara.leg.br/api/v2/deputados/178918",
      "nome": "KAIO MANIÇOBA",
      "siglaPartido": "PMDB",
      "uriPartido": "https://dadosabertos.camara.leg.br/api/v2/partidos/36800",
      "siglaUf": "PE",
      "idLegislatura": 55,
      "urlFoto": "http://www.camara.leg.br/internet/deputado/bandep/178918.jpg"
    },
    {
      "id": 160659,
      "uri": "https://dadosabertos.camara.leg.br/api/v2/deputados/160659",
      "nome": "KEIKO OTA",
      "siglaPartido": "PSB",
      "uriPartido": "https://dadosabertos.camara.leg.br/api/v2/partidos/36832",
      "siglaUf": "SP",
      "idLegislatura": 55,
      "urlFoto": "http://www.camara.leg.br/internet/deputado/bandep/160659.jpg"
    },
    {
      "id": 151208,
      "uri": "https://dadosabertos.camara.leg.br/api/v2/deputados/151208",
      "nome": "LAERCIO OLIVEIRA",
      "siglaPartido": "SD",
      "uriPartido": "https://dadosabertos.camara.leg.br/api/v2/partidos/36765",
      "siglaUf": "SE",
      "idLegislatura": 55,
      "urlFoto": "http://www.camara.leg.br/internet/deputado/bandep/151208.jpg"
    },
    {
      "id": 141478,
      "uri": "https://dadosabertos.camara.leg.br/api/v2/deputados/141478",
      "nome": "LAERTE BESSA",
      "siglaPartido": "PR",
      "uriPartido": "https://dadosabertos.camara.leg.br/api/v2/partidos/36814",
      "siglaUf": "DF",
      "idLegislatura": 55,
      "urlFoto": "http://www.camara.leg.br/internet/deputado/bandep/141478.jpg"
    },
    {
      "id": 178894,
      "uri": "https://dadosabertos.camara.leg.br/api/v2/deputados/178894",
      "nome": "LAUDIVIO CARVALHO",
      "siglaPartido": "SD",
      "uriPartido": "https://dadosabertos.camara.leg.br/api/v2/partidos/36765",
      "siglaUf": "MG",
      "idLegislatura": 55,
      "urlFoto": "http://www.camara.leg.br/internet/deputado/bandep/178894.jpg"
    },
    {
      "id": 74856,
      "uri": "https://dadosabertos.camara.leg.br/api/v2/deputados/74856",
      "nome": "LAURA CARNEIRO",
      "siglaPartido": "PMDB",
      "uriPartido": "https://dadosabertos.camara.leg.br/api/v2/partidos/36800",
      "siglaUf": "RJ",
      "idLegislatura": 55,
      "urlFoto": "http://www.camara.leg.br/internet/deputado/bandep/74856.jpg"
    },
    {
      "id": 141480,
      "uri": "https://dadosabertos.camara.leg.br/api/v2/deputados/141480",
      "nome": "LÁZARO BOTELHO",
      "siglaPartido": "PP",
      "uriPartido": "https://dadosabertos.camara.leg.br/api/v2/partidos/36809",
      "siglaUf": "TO",
      "idLegislatura": 55,
      "urlFoto": "http://www.camara.leg.br/internet/deputado/bandep/141480.jpg"
    },
    {
      "id": 178832,
      "uri": "https://dadosabertos.camara.leg.br/api/v2/deputados/178832",
      "nome": "LEANDRE",
      "siglaPartido": "PV",
      "uriPartido": "https://dadosabertos.camara.leg.br/api/v2/partidos/36851",
      "siglaUf": "PR",
      "idLegislatura": 55,
      "urlFoto": "http://www.camara.leg.br/internet/deputado/bandep/178832.jpg"
    },
    {
      "id": 141562,
      "uri": "https://dadosabertos.camara.leg.br/api/v2/deputados/141562",
      "nome": "LELO COIMBRA",
      "siglaPartido": "PMDB",
      "uriPartido": "https://dadosabertos.camara.leg.br/api/v2/partidos/36800",
      "siglaUf": "ES",
      "idLegislatura": 55,
      "urlFoto": "http://www.camara.leg.br/internet/deputado/bandep/141562.jpg"
    },
    {
      "id": 178825,
      "uri": "https://dadosabertos.camara.leg.br/api/v2/deputados/178825",
      "nome": "LEO DE BRITO",
      "siglaPartido": "PT",
      "uriPartido": "https://dadosabertos.camara.leg.br/api/v2/partidos/36844",
      "siglaUf": "AC",
      "idLegislatura": 55,
      "urlFoto": "http://www.camara.leg.br/internet/deputado/bandep/178825.jpg"
    },
    {
      "id": 74156,
      "uri": "https://dadosabertos.camara.leg.br/api/v2/deputados/74156",
      "nome": "LEONARDO MONTEIRO",
      "siglaPartido": "PT",
      "uriPartido": "https://dadosabertos.camara.leg.br/api/v2/partidos/36844",
      "siglaUf": "MG",
      "idLegislatura": 55,
      "urlFoto": "http://www.camara.leg.br/internet/deputado/bandep/74156.jpg"
    },
    {
      "id": 74254,
      "uri": "https://dadosabertos.camara.leg.br/api/v2/deputados/74254",
      "nome": "LEONARDO PICCIANI",
      "siglaPartido": "PMDB",
      "uriPartido": "https://dadosabertos.camara.leg.br/api/v2/partidos/36800",
      "siglaUf": "RJ",
      "idLegislatura": 55,
      "urlFoto": "http://www.camara.leg.br/internet/deputado/bandep/74254.jpg"
    },
    {
      "id": 141482,
      "uri": "https://dadosabertos.camara.leg.br/api/v2/deputados/141482",
      "nome": "LEONARDO QUINTÃO",
      "siglaPartido": "PMDB",
      "uriPartido": "https://dadosabertos.camara.leg.br/api/v2/partidos/36800",
      "siglaUf": "MG",
      "idLegislatura": 55,
      "urlFoto": "http://www.camara.leg.br/internet/deputado/bandep/141482.jpg"
    },
    {
      "id": 74299,
      "uri": "https://dadosabertos.camara.leg.br/api/v2/deputados/74299",
      "nome": "LEÔNIDAS CRISTINO",
      "siglaPartido": "PDT",
      "uriPartido": "https://dadosabertos.camara.leg.br/api/v2/partidos/36786",
      "siglaUf": "CE",
      "idLegislatura": 55,
      "urlFoto": "http://www.camara.leg.br/internet/deputado/bandep/74299.jpg"
    },
    {
      "id": 160663,
      "uri": "https://dadosabertos.camara.leg.br/api/v2/deputados/160663",
      "nome": "LEOPOLDO MEYER",
      "siglaPartido": "PSB",
      "uriPartido": "https://dadosabertos.camara.leg.br/api/v2/partidos/36832",
      "siglaUf": "PR",
      "idLegislatura": 55,
      "urlFoto": "http://www.camara.leg.br/internet/deputado/bandep/160663.jpg"
    },
    {
      "id": 74585,
      "uri": "https://dadosabertos.camara.leg.br/api/v2/deputados/74585",
      "nome": "LINCOLN PORTELA",
      "siglaPartido": "PRB",
      "uriPartido": "https://dadosabertos.camara.leg.br/api/v2/partidos/36815",
      "siglaUf": "MG",
      "idLegislatura": 55,
      "urlFoto": "http://www.camara.leg.br/internet/deputado/bandep/74585.jpg"
    },
    {
      "id": 141483,
      "uri": "https://dadosabertos.camara.leg.br/api/v2/deputados/141483",
      "nome": "LINDOMAR GARÇON",
      "siglaPartido": "PRB",
      "uriPartido": "https://dadosabertos.camara.leg.br/api/v2/partidos/36815",
      "siglaUf": "RO",
      "idLegislatura": 55,
      "urlFoto": "http://www.camara.leg.br/internet/deputado/bandep/141483.jpg"
    },
    {
      "id": 74277,
      "uri": "https://dadosabertos.camara.leg.br/api/v2/deputados/74277",
      "nome": "LOBBE NETO",
      "siglaPartido": "PSDB",
      "uriPartido": "https://dadosabertos.camara.leg.br/api/v2/partidos/36835",
      "siglaUf": "SP",
      "idLegislatura": 55,
      "urlFoto": "http://www.camara.leg.br/internet/deputado/bandep/74277.jpg"
    },
    {
      "id": 196358,
      "uri": "https://dadosabertos.camara.leg.br/api/v2/deputados/196358",
      "nome": "LOURIVAL GOMES",
      "siglaPartido": "PODE",
      "uriPartido": "https://dadosabertos.camara.leg.br/api/v2/partidos/36896",
      "siglaUf": "RJ",
      "idLegislatura": 55,
      "urlFoto": "http://www.camara.leg.br/internet/deputado/bandep/196358.jpg"
    },
    {
      "id": 81366,
      "uri": "https://dadosabertos.camara.leg.br/api/v2/deputados/81366",
      "nome": "LUANA COSTA",
      "siglaPartido": "PSB",
      "uriPartido": "https://dadosabertos.camara.leg.br/api/v2/partidos/36832",
      "siglaUf": "MA",
      "idLegislatura": 55,
      "urlFoto": "http://www.camara.leg.br/internet/deputado/bandep/81366.jpg"
    },
    {
      "id": 178879,
      "uri": "https://dadosabertos.camara.leg.br/api/v2/deputados/178879",
      "nome": "LUCAS VERGILIO",
      "siglaPartido": "SD",
      "uriPartido": "https://dadosabertos.camara.leg.br/api/v2/partidos/36765",
      "siglaUf": "GO",
      "idLegislatura": 55,
      "urlFoto": "http://www.camara.leg.br/internet/deputado/bandep/178879.jpg"
    },
    {
      "id": 160628,
      "uri": "https://dadosabertos.camara.leg.br/api/v2/deputados/160628",
      "nome": "LUCIANA SANTOS",
      "siglaPartido": "PCdoB",
      "uriPartido": "https://dadosabertos.camara.leg.br/api/v2/partidos/36779",
      "siglaUf": "PE",
      "idLegislatura": 55,
      "urlFoto": "http://www.camara.leg.br/internet/deputado/bandep/160628.jpg"
    },
    {
      "id": 74478,
      "uri": "https://dadosabertos.camara.leg.br/api/v2/deputados/74478",
      "nome": "LUCIANO BIVAR",
      "siglaPartido": "PSL",
      "uriPartido": "https://dadosabertos.camara.leg.br/api/v2/partidos/36837",
      "siglaUf": "PE",
      "idLegislatura": 55,
      "urlFoto": "http://www.camara.leg.br/internet/deputado/bandep/74478.jpg"
    },
    {
      "id": 178931,
      "uri": "https://dadosabertos.camara.leg.br/api/v2/deputados/178931",
      "nome": "LUCIANO DUCCI",
      "siglaPartido": "PSB",
      "uriPartido": "https://dadosabertos.camara.leg.br/api/v2/partidos/36832",
      "siglaUf": "PR",
      "idLegislatura": 55,
      "urlFoto": "http://www.camara.leg.br/internet/deputado/bandep/178931.jpg"
    },
    {
      "id": 178954,
      "uri": "https://dadosabertos.camara.leg.br/api/v2/deputados/178954",
      "nome": "LUCIO MOSQUINI",
      "siglaPartido": "PMDB",
      "uriPartido": "https://dadosabertos.camara.leg.br/api/v2/partidos/36800",
      "siglaUf": "RO",
      "idLegislatura": 55,
      "urlFoto": "http://www.camara.leg.br/internet/deputado/bandep/178954.jpg"
    },
    {
      "id": 141484,
      "uri": "https://dadosabertos.camara.leg.br/api/v2/deputados/141484",
      "nome": "LÚCIO VALE",
      "siglaPartido": "PR",
      "uriPartido": "https://dadosabertos.camara.leg.br/api/v2/partidos/36814",
      "siglaUf": "PA",
      "idLegislatura": 55,
      "urlFoto": "http://www.camara.leg.br/internet/deputado/bandep/141484.jpg"
    },
    {
      "id": 94931,
      "uri": "https://dadosabertos.camara.leg.br/api/v2/deputados/94931",
      "nome": "LUCIO VIEIRA LIMA",
      "siglaPartido": "PMDB",
      "uriPartido": "https://dadosabertos.camara.leg.br/api/v2/partidos/36800",
      "siglaUf": "BA",
      "idLegislatura": 55,
      "urlFoto": "http://www.camara.leg.br/internet/deputado/bandep/94931.jpg"
    },
    {
      "id": 73483,
      "uri": "https://dadosabertos.camara.leg.br/api/v2/deputados/73483",
      "nome": "LUIS CARLOS HEINZE",
      "siglaPartido": "PP",
      "uriPartido": "https://dadosabertos.camara.leg.br/api/v2/partidos/36809",
      "siglaUf": "RS",
      "idLegislatura": 55,
      "urlFoto": "http://www.camara.leg.br/internet/deputado/bandep/73483.jpg"
    },
    {
      "id": 160510,
      "uri": "https://dadosabertos.camara.leg.br/api/v2/deputados/160510",
      "nome": "LUIS TIBÉ",
      "siglaPartido": "PTdoB",
      "uriPartido": "https://dadosabertos.camara.leg.br/api/v2/partidos/36847",
      "siglaUf": "MG",
      "idLegislatura": 55,
      "urlFoto": "http://www.camara.leg.br/internet/deputado/bandep/160510.jpg"
    },
    {
      "id": 141485,
      "uri": "https://dadosabertos.camara.leg.br/api/v2/deputados/141485",
      "nome": "LUIZ CARLOS BUSATO",
      "siglaPartido": "PTB",
      "uriPartido": "https://dadosabertos.camara.leg.br/api/v2/partidos/36845",
      "siglaUf": "RS",
      "idLegislatura": 55,
      "urlFoto": "http://www.camara.leg.br/internet/deputado/bandep/141485.jpg"
    },
    {
      "id": 73778,
      "uri": "https://dadosabertos.camara.leg.br/api/v2/deputados/73778",
      "nome": "LUIZ CARLOS HAULY",
      "siglaPartido": "PSDB",
      "uriPartido": "https://dadosabertos.camara.leg.br/api/v2/partidos/36835",
      "siglaUf": "PR",
      "idLegislatura": 55,
      "urlFoto": "http://www.camara.leg.br/internet/deputado/bandep/73778.jpg"
    },
    {
      "id": 178802,
      "uri": "https://dadosabertos.camara.leg.br/api/v2/deputados/178802",
      "nome": "LUIZ CARLOS RAMOS ",
      "siglaPartido": "PODE",
      "uriPartido": "https://dadosabertos.camara.leg.br/api/v2/partidos/36896",
      "siglaUf": "RJ",
      "idLegislatura": 55,
      "urlFoto": "http://www.camara.leg.br/internet/deputado/bandep/178802.jpg"
    },
    {
      "id": 178955,
      "uri": "https://dadosabertos.camara.leg.br/api/v2/deputados/178955",
      "nome": "LUIZ CLÁUDIO",
      "siglaPartido": "PR",
      "uriPartido": "https://dadosabertos.camara.leg.br/api/v2/partidos/36814",
      "siglaUf": "RO",
      "idLegislatura": 55,
      "urlFoto": "http://www.camara.leg.br/internet/deputado/bandep/178955.jpg"
    },
    {
      "id": 74041,
      "uri": "https://dadosabertos.camara.leg.br/api/v2/deputados/74041",
      "nome": "LUIZ COUTO",
      "siglaPartido": "PT",
      "uriPartido": "https://dadosabertos.camara.leg.br/api/v2/partidos/36844",
      "siglaUf": "PB",
      "idLegislatura": 55,
      "urlFoto": "http://www.camara.leg.br/internet/deputado/bandep/74041.jpg"
    },
    {
      "id": 141487,
      "uri": "https://dadosabertos.camara.leg.br/api/v2/deputados/141487",
      "nome": "LUIZ FERNANDO FARIA",
      "siglaPartido": "PP",
      "uriPartido": "https://dadosabertos.camara.leg.br/api/v2/partidos/36809",
      "siglaUf": "MG",
      "idLegislatura": 55,
      "urlFoto": "http://www.camara.leg.br/internet/deputado/bandep/141487.jpg"
    },
    {
      "id": 178982,
      "uri": "https://dadosabertos.camara.leg.br/api/v2/deputados/178982",
      "nome": "LUIZ LAURO FILHO",
      "siglaPartido": "PSB",
      "uriPartido": "https://dadosabertos.camara.leg.br/api/v2/partidos/36832",
      "siglaUf": "SP",
      "idLegislatura": 55,
      "urlFoto": "http://www.camara.leg.br/internet/deputado/bandep/178982.jpg"
    },
    {
      "id": 162332,
      "uri": "https://dadosabertos.camara.leg.br/api/v2/deputados/162332",
      "nome": "LUIZ NISHIMORI",
      "siglaPartido": "PR",
      "uriPartido": "https://dadosabertos.camara.leg.br/api/v2/partidos/36814",
      "siglaUf": "PR",
      "idLegislatura": 55,
      "urlFoto": "http://www.camara.leg.br/internet/deputado/bandep/162332.jpg"
    },
    {
      "id": 74688,
      "uri": "https://dadosabertos.camara.leg.br/api/v2/deputados/74688",
      "nome": "LUIZ SÉRGIO",
      "siglaPartido": "PT",
      "uriPartido": "https://dadosabertos.camara.leg.br/api/v2/partidos/36844",
      "siglaUf": "RJ",
      "idLegislatura": 55,
      "urlFoto": "http://www.camara.leg.br/internet/deputado/bandep/74688.jpg"
    },
    {
      "id": 74784,
      "uri": "https://dadosabertos.camara.leg.br/api/v2/deputados/74784",
      "nome": "LUIZA ERUNDINA",
      "siglaPartido": "PSOL",
      "uriPartido": "https://dadosabertos.camara.leg.br/api/v2/partidos/36839",
      "siglaUf": "SP",
      "idLegislatura": 55,
      "urlFoto": "http://www.camara.leg.br/internet/deputado/bandep/74784.jpg"
    },
    {
      "id": 178866,
      "uri": "https://dadosabertos.camara.leg.br/api/v2/deputados/178866",
      "nome": "LUIZIANNE LINS",
      "siglaPartido": "PT",
      "uriPartido": "https://dadosabertos.camara.leg.br/api/v2/partidos/36844",
      "siglaUf": "CE",
      "idLegislatura": 55,
      "urlFoto": "http://www.camara.leg.br/internet/deputado/bandep/178866.jpg"
    },
    {
      "id": 198198,
      "uri": "https://dadosabertos.camara.leg.br/api/v2/deputados/198198",
      "nome": "LUZIA FERREIRA",
      "siglaPartido": "PPS",
      "uriPartido": "https://dadosabertos.camara.leg.br/api/v2/partidos/36813",
      "siglaUf": "MG",
      "idLegislatura": 55,
      "urlFoto": "http://www.camara.leg.br/internet/deputado/bandep/198198.jpg"
    },
    {
      "id": 178867,
      "uri": "https://dadosabertos.camara.leg.br/api/v2/deputados/178867",
      "nome": "MACEDO",
      "siglaPartido": "PP",
      "uriPartido": "https://dadosabertos.camara.leg.br/api/v2/partidos/36809",
      "siglaUf": "CE",
      "idLegislatura": 55,
      "urlFoto": "http://www.camara.leg.br/internet/deputado/bandep/178867.jpg"
    },
    {
      "id": 166402,
      "uri": "https://dadosabertos.camara.leg.br/api/v2/deputados/166402",
      "nome": "MAGDA MOFATTO",
      "siglaPartido": "PR",
      "uriPartido": "https://dadosabertos.camara.leg.br/api/v2/partidos/36814",
      "siglaUf": "GO",
      "idLegislatura": 55,
      "urlFoto": "http://www.camara.leg.br/internet/deputado/bandep/166402.jpg"
    },
    {
      "id": 151965,
      "uri": "https://dadosabertos.camara.leg.br/api/v2/deputados/151965",
      "nome": "MAIA FILHO",
      "siglaPartido": "PP",
      "uriPartido": "https://dadosabertos.camara.leg.br/api/v2/partidos/36809",
      "siglaUf": "PI",
      "idLegislatura": 55,
      "urlFoto": "http://www.camara.leg.br/internet/deputado/bandep/151965.jpg"
    },
    {
      "id": 178826,
      "uri": "https://dadosabertos.camara.leg.br/api/v2/deputados/178826",
      "nome": "MAJOR OLIMPIO",
      "siglaPartido": "SD",
      "uriPartido": "https://dadosabertos.camara.leg.br/api/v2/partidos/36765",
      "siglaUf": "SP",
      "idLegislatura": 55,
      "urlFoto": "http://www.camara.leg.br/internet/deputado/bandep/178826.jpg"
    },
    {
      "id": 160633,
      "uri": "https://dadosabertos.camara.leg.br/api/v2/deputados/160633",
      "nome": "MANDETTA",
      "siglaPartido": "DEM",
      "uriPartido": "https://dadosabertos.camara.leg.br/api/v2/partidos/36769",
      "siglaUf": "MS",
      "idLegislatura": 55,
      "urlFoto": "http://www.camara.leg.br/internet/deputado/bandep/160633.jpg"
    },
    {
      "id": 141490,
      "uri": "https://dadosabertos.camara.leg.br/api/v2/deputados/141490",
      "nome": "MANOEL JUNIOR",
      "siglaPartido": "PMDB",
      "uriPartido": "https://dadosabertos.camara.leg.br/api/v2/partidos/36800",
      "siglaUf": "PB",
      "idLegislatura": 55,
      "urlFoto": "http://www.camara.leg.br/internet/deputado/bandep/141490.jpg"
    },
    {
      "id": 160565,
      "uri": "https://dadosabertos.camara.leg.br/api/v2/deputados/160565",
      "nome": "MARA GABRILLI",
      "siglaPartido": "PSDB",
      "uriPartido": "https://dadosabertos.camara.leg.br/api/v2/partidos/36835",
      "siglaUf": "SP",
      "idLegislatura": 55,
      "urlFoto": "http://www.camara.leg.br/internet/deputado/bandep/160565.jpg"
    },
    {
      "id": 160660,
      "uri": "https://dadosabertos.camara.leg.br/api/v2/deputados/160660",
      "nome": "MARCELO AGUIAR",
      "siglaPartido": "DEM",
      "uriPartido": "https://dadosabertos.camara.leg.br/api/v2/partidos/36769",
      "siglaUf": "SP",
      "idLegislatura": 55,
      "urlFoto": "http://www.camara.leg.br/internet/deputado/bandep/160660.jpg"
    },
    {
      "id": 179000,
      "uri": "https://dadosabertos.camara.leg.br/api/v2/deputados/179000",
      "nome": "MARCELO ÁLVARO ANTÔNIO",
      "siglaPartido": "PR",
      "uriPartido": "https://dadosabertos.camara.leg.br/api/v2/partidos/36814",
      "siglaUf": "MG",
      "idLegislatura": 55,
      "urlFoto": "http://www.camara.leg.br/internet/deputado/bandep/179000.jpg"
    },
    {
      "id": 146788,
      "uri": "https://dadosabertos.camara.leg.br/api/v2/deputados/146788",
      "nome": "MARCELO ARO",
      "siglaPartido": "PHS",
      "uriPartido": "https://dadosabertos.camara.leg.br/api/v2/partidos/36793",
      "siglaUf": "MG",
      "idLegislatura": 55,
      "urlFoto": "http://www.camara.leg.br/internet/deputado/bandep/146788.jpg"
    },
    {
      "id": 178932,
      "uri": "https://dadosabertos.camara.leg.br/api/v2/deputados/178932",
      "nome": "MARCELO BELINATI",
      "siglaPartido": "PP",
      "uriPartido": "https://dadosabertos.camara.leg.br/api/v2/partidos/36809",
      "siglaUf": "PR",
      "idLegislatura": 55,
      "urlFoto": "http://www.camara.leg.br/internet/deputado/bandep/178932.jpg"
    },
    {
      "id": 74460,
      "uri": "https://dadosabertos.camara.leg.br/api/v2/deputados/74460",
      "nome": "MARCELO CASTRO",
      "siglaPartido": "PMDB",
      "uriPartido": "https://dadosabertos.camara.leg.br/api/v2/partidos/36800",
      "siglaUf": "PI",
      "idLegislatura": 55,
      "urlFoto": "http://www.camara.leg.br/internet/deputado/bandep/74460.jpg"
    },
    {
      "id": 195826,
      "uri": "https://dadosabertos.camara.leg.br/api/v2/deputados/195826",
      "nome": "MARCELO DELAROLI",
      "siglaPartido": "PR",
      "uriPartido": "https://dadosabertos.camara.leg.br/api/v2/partidos/36814",
      "siglaUf": "RJ",
      "idLegislatura": 55,
      "urlFoto": "http://www.camara.leg.br/internet/deputado/bandep/195826.jpg"
    },
    {
      "id": 76287,
      "uri": "https://dadosabertos.camara.leg.br/api/v2/deputados/76287",
      "nome": "MARCELO MATOS",
      "siglaPartido": "PHS",
      "uriPartido": "https://dadosabertos.camara.leg.br/api/v2/partidos/36793",
      "siglaUf": "RJ",
      "idLegislatura": 55,
      "urlFoto": "http://www.camara.leg.br/internet/deputado/bandep/76287.jpg"
    },
    {
      "id": 118594,
      "uri": "https://dadosabertos.camara.leg.br/api/v2/deputados/118594",
      "nome": "MARCELO SQUASSONI",
      "siglaPartido": "PRB",
      "uriPartido": "https://dadosabertos.camara.leg.br/api/v2/partidos/36815",
      "siglaUf": "SP",
      "idLegislatura": 55,
      "urlFoto": "http://www.camara.leg.br/internet/deputado/bandep/118594.jpg"
    },
    {
      "id": 178983,
      "uri": "https://dadosabertos.camara.leg.br/api/v2/deputados/178983",
      "nome": "MARCIO ALVINO",
      "siglaPartido": "PR",
      "uriPartido": "https://dadosabertos.camara.leg.br/api/v2/partidos/36814",
      "siglaUf": "SP",
      "idLegislatura": 55,
      "urlFoto": "http://www.camara.leg.br/internet/deputado/bandep/178983.jpg"
    },
    {
      "id": 179001,
      "uri": "https://dadosabertos.camara.leg.br/api/v2/deputados/179001",
      "nome": "MÁRCIO BIOLCHI",
      "siglaPartido": "PMDB",
      "uriPartido": "https://dadosabertos.camara.leg.br/api/v2/partidos/36800",
      "siglaUf": "RS",
      "idLegislatura": 55,
      "urlFoto": "http://www.camara.leg.br/internet/deputado/bandep/179001.jpg"
    },
    {
      "id": 150418,
      "uri": "https://dadosabertos.camara.leg.br/api/v2/deputados/150418",
      "nome": "MÁRCIO MARINHO",
      "siglaPartido": "PRB",
      "uriPartido": "https://dadosabertos.camara.leg.br/api/v2/partidos/36815",
      "siglaUf": "BA",
      "idLegislatura": 55,
      "urlFoto": "http://www.camara.leg.br/internet/deputado/bandep/150418.jpg"
    },
    {
      "id": 178899,
      "uri": "https://dadosabertos.camara.leg.br/api/v2/deputados/178899",
      "nome": "MARCIO MONTEIRO",
      "siglaPartido": "PSDB",
      "uriPartido": "https://dadosabertos.camara.leg.br/api/v2/partidos/36835",
      "siglaUf": "MS",
      "idLegislatura": 55,
      "urlFoto": "http://www.camara.leg.br/internet/deputado/bandep/178899.jpg"
    },
    {
      "id": 178942,
      "uri": "https://dadosabertos.camara.leg.br/api/v2/deputados/178942",
      "nome": "MARCO ANTÔNIO CABRAL",
      "siglaPartido": "PMDB",
      "uriPartido": "https://dadosabertos.camara.leg.br/api/v2/partidos/36800",
      "siglaUf": "RJ",
      "idLegislatura": 55,
      "urlFoto": "http://www.camara.leg.br/internet/deputado/bandep/178942.jpg"
    },
    {
      "id": 133373,
      "uri": "https://dadosabertos.camara.leg.br/api/v2/deputados/133373",
      "nome": "MARCO MAIA",
      "siglaPartido": "PT",
      "uriPartido": "https://dadosabertos.camara.leg.br/api/v2/partidos/36844",
      "siglaUf": "RS",
      "idLegislatura": 55,
      "urlFoto": "http://www.camara.leg.br/internet/deputado/bandep/133373.jpg"
    },
    {
      "id": 160536,
      "uri": "https://dadosabertos.camara.leg.br/api/v2/deputados/160536",
      "nome": "MARCO TEBALDI",
      "siglaPartido": "PSDB",
      "uriPartido": "https://dadosabertos.camara.leg.br/api/v2/partidos/36835",
      "siglaUf": "SC",
      "idLegislatura": 55,
      "urlFoto": "http://www.camara.leg.br/internet/deputado/bandep/160536.jpg"
    },
    {
      "id": 160535,
      "uri": "https://dadosabertos.camara.leg.br/api/v2/deputados/160535",
      "nome": "MARCON",
      "siglaPartido": "PT",
      "uriPartido": "https://dadosabertos.camara.leg.br/api/v2/partidos/36844",
      "siglaUf": "RS",
      "idLegislatura": 55,
      "urlFoto": "http://www.camara.leg.br/internet/deputado/bandep/160535.jpg"
    },
    {
      "id": 74470,
      "uri": "https://dadosabertos.camara.leg.br/api/v2/deputados/74470",
      "nome": "MARCONDES GADELHA",
      "siglaPartido": "PSC",
      "uriPartido": "https://dadosabertos.camara.leg.br/api/v2/partidos/36833",
      "siglaUf": "PB",
      "idLegislatura": 55,
      "urlFoto": "http://www.camara.leg.br/internet/deputado/bandep/74470.jpg"
    },
    {
      "id": 178880,
      "uri": "https://dadosabertos.camara.leg.br/api/v2/deputados/178880",
      "nome": "MARCOS ABRÃO",
      "siglaPartido": "PPS",
      "uriPartido": "https://dadosabertos.camara.leg.br/api/v2/partidos/36813",
      "siglaUf": "GO",
      "idLegislatura": 55,
      "urlFoto": "http://www.camara.leg.br/internet/deputado/bandep/178880.jpg"
    },
    {
      "id": 74634,
      "uri": "https://dadosabertos.camara.leg.br/api/v2/deputados/74634",
      "nome": "MARCOS MEDRADO",
      "siglaPartido": "PODE",
      "uriPartido": "https://dadosabertos.camara.leg.br/api/v2/partidos/36896",
      "siglaUf": "BA",
      "idLegislatura": 55,
      "urlFoto": "http://www.camara.leg.br/internet/deputado/bandep/74634.jpg"
    },
    {
      "id": 141500,
      "uri": "https://dadosabertos.camara.leg.br/api/v2/deputados/141500",
      "nome": "MARCOS MONTES",
      "siglaPartido": "PSD",
      "uriPartido": "https://dadosabertos.camara.leg.br/api/v2/partidos/36834",
      "siglaUf": "MG",
      "idLegislatura": 55,
      "urlFoto": "http://www.camara.leg.br/internet/deputado/bandep/141500.jpg"
    },
    {
      "id": 178852,
      "uri": "https://dadosabertos.camara.leg.br/api/v2/deputados/178852",
      "nome": "MARCOS REATEGUI",
      "siglaPartido": "PSD",
      "uriPartido": "https://dadosabertos.camara.leg.br/api/v2/partidos/36834",
      "siglaUf": "AP",
      "idLegislatura": 55,
      "urlFoto": "http://www.camara.leg.br/internet/deputado/bandep/178852.jpg"
    },
    {
      "id": 167722,
      "uri": "https://dadosabertos.camara.leg.br/api/v2/deputados/167722",
      "nome": "MARCOS ROGÉRIO",
      "siglaPartido": "DEM",
      "uriPartido": "https://dadosabertos.camara.leg.br/api/v2/partidos/36769",
      "siglaUf": "RO",
      "idLegislatura": 55,
      "urlFoto": "http://www.camara.leg.br/internet/deputado/bandep/167722.jpg"
    },
    {
      "id": 178850,
      "uri": "https://dadosabertos.camara.leg.br/api/v2/deputados/178850",
      "nome": "MARCOS ROTTA",
      "siglaPartido": "PMDB",
      "uriPartido": "https://dadosabertos.camara.leg.br/api/v2/partidos/36800",
      "siglaUf": "AM",
      "idLegislatura": 55,
      "urlFoto": "http://www.camara.leg.br/internet/deputado/bandep/178850.jpg"
    },
    {
      "id": 178943,
      "uri": "https://dadosabertos.camara.leg.br/api/v2/deputados/178943",
      "nome": "MARCOS SOARES",
      "siglaPartido": "DEM",
      "uriPartido": "https://dadosabertos.camara.leg.br/api/v2/partidos/36769",
      "siglaUf": "RJ",
      "idLegislatura": 55,
      "urlFoto": "http://www.camara.leg.br/internet/deputado/bandep/178943.jpg"
    },
    {
      "id": 159238,
      "uri": "https://dadosabertos.camara.leg.br/api/v2/deputados/159238",
      "nome": "MARCUS PESTANA",
      "siglaPartido": "PSDB",
      "uriPartido": "https://dadosabertos.camara.leg.br/api/v2/partidos/36835",
      "siglaUf": "MG",
      "idLegislatura": 55,
      "urlFoto": "http://www.camara.leg.br/internet/deputado/bandep/159238.jpg"
    },
    {
      "id": 74235,
      "uri": "https://dadosabertos.camara.leg.br/api/v2/deputados/74235",
      "nome": "MARCUS VICENTE",
      "siglaPartido": "PP",
      "uriPartido": "https://dadosabertos.camara.leg.br/api/v2/partidos/36809",
      "siglaUf": "ES",
      "idLegislatura": 55,
      "urlFoto": "http://www.camara.leg.br/internet/deputado/bandep/74235.jpg"
    },
    {
      "id": 171619,
      "uri": "https://dadosabertos.camara.leg.br/api/v2/deputados/171619",
      "nome": "MARGARIDA SALOMÃO",
      "siglaPartido": "PT",
      "uriPartido": "https://dadosabertos.camara.leg.br/api/v2/partidos/36844",
      "siglaUf": "MG",
      "idLegislatura": 55,
      "urlFoto": "http://www.camara.leg.br/internet/deputado/bandep/171619.jpg"
    },
    {
      "id": 74398,
      "uri": "https://dadosabertos.camara.leg.br/api/v2/deputados/74398",
      "nome": "MARIA DO ROSÁRIO",
      "siglaPartido": "PT",
      "uriPartido": "https://dadosabertos.camara.leg.br/api/v2/partidos/36844",
      "siglaUf": "RS",
      "idLegislatura": 55,
      "urlFoto": "http://www.camara.leg.br/internet/deputado/bandep/74398.jpg"
    },
    {
      "id": 64960,
      "uri": "https://dadosabertos.camara.leg.br/api/v2/deputados/64960",
      "nome": "MARIA HELENA",
      "siglaPartido": "PSB",
      "uriPartido": "https://dadosabertos.camara.leg.br/api/v2/partidos/36832",
      "siglaUf": "RR",
      "idLegislatura": 55,
      "urlFoto": "http://www.camara.leg.br/internet/deputado/bandep/64960.jpg"
    },
    {
      "id": 178956,
      "uri": "https://dadosabertos.camara.leg.br/api/v2/deputados/178956",
      "nome": "MARIANA CARVALHO",
      "siglaPartido": "PSDB",
      "uriPartido": "https://dadosabertos.camara.leg.br/api/v2/partidos/36835",
      "siglaUf": "RO",
      "idLegislatura": 55,
      "urlFoto": "http://www.camara.leg.br/internet/deputado/bandep/178956.jpg"
    },
    {
      "id": 178919,
      "uri": "https://dadosabertos.camara.leg.br/api/v2/deputados/178919",
      "nome": "MARINALDO ROSENDO",
      "siglaPartido": "PSB",
      "uriPartido": "https://dadosabertos.camara.leg.br/api/v2/partidos/36832",
      "siglaUf": "PE",
      "idLegislatura": 55,
      "urlFoto": "http://www.camara.leg.br/internet/deputado/bandep/178919.jpg"
    },
    {
      "id": 74177,
      "uri": "https://dadosabertos.camara.leg.br/api/v2/deputados/74177",
      "nome": "MARINHA RAUPP",
      "siglaPartido": "PMDB",
      "uriPartido": "https://dadosabertos.camara.leg.br/api/v2/partidos/36800",
      "siglaUf": "RO",
      "idLegislatura": 55,
      "urlFoto": "http://www.camara.leg.br/internet/deputado/bandep/74177.jpg"
    },
    {
      "id": 74158,
      "uri": "https://dadosabertos.camara.leg.br/api/v2/deputados/74158",
      "nome": "MÁRIO HERINGER",
      "siglaPartido": "PDT",
      "uriPartido": "https://dadosabertos.camara.leg.br/api/v2/partidos/36786",
      "siglaUf": "MG",
      "idLegislatura": 55,
      "urlFoto": "http://www.camara.leg.br/internet/deputado/bandep/74158.jpg"
    },
    {
      "id": 178858,
      "uri": "https://dadosabertos.camara.leg.br/api/v2/deputados/178858",
      "nome": "MÁRIO NEGROMONTE JR.",
      "siglaPartido": "PP",
      "uriPartido": "https://dadosabertos.camara.leg.br/api/v2/partidos/36809",
      "siglaUf": "BA",
      "idLegislatura": 55,
      "urlFoto": "http://www.camara.leg.br/internet/deputado/bandep/178858.jpg"
    },
    {
      "id": 181315,
      "uri": "https://dadosabertos.camara.leg.br/api/v2/deputados/181315",
      "nome": "MARQUINHO MENDES",
      "siglaPartido": "PMDB",
      "uriPartido": "https://dadosabertos.camara.leg.br/api/v2/partidos/36800",
      "siglaUf": "RJ",
      "idLegislatura": 55,
      "urlFoto": "http://www.camara.leg.br/internet/deputado/bandep/181315.jpg"
    },
    {
      "id": 178843,
      "uri": "https://dadosabertos.camara.leg.br/api/v2/deputados/178843",
      "nome": "MARX BELTRÃO",
      "siglaPartido": "PMDB",
      "uriPartido": "https://dadosabertos.camara.leg.br/api/v2/partidos/36800",
      "siglaUf": "AL",
      "idLegislatura": 55,
      "urlFoto": "http://www.camara.leg.br/internet/deputado/bandep/178843.jpg"
    },
    {
      "id": 74050,
      "uri": "https://dadosabertos.camara.leg.br/api/v2/deputados/74050",
      "nome": "MAURÍCIO QUINTELLA LESSA",
      "siglaPartido": "PR",
      "uriPartido": "https://dadosabertos.camara.leg.br/api/v2/partidos/36814",
      "siglaUf": "AL",
      "idLegislatura": 55,
      "urlFoto": "http://www.camara.leg.br/internet/deputado/bandep/74050.jpg"
    },
    {
      "id": 73588,
      "uri": "https://dadosabertos.camara.leg.br/api/v2/deputados/73588",
      "nome": "MAURO BENEVIDES",
      "siglaPartido": "PMDB",
      "uriPartido": "https://dadosabertos.camara.leg.br/api/v2/partidos/36800",
      "siglaUf": "CE",
      "idLegislatura": 55,
      "urlFoto": "http://www.camara.leg.br/internet/deputado/bandep/73588.jpg"
    },
    {
      "id": 74749,
      "uri": "https://dadosabertos.camara.leg.br/api/v2/deputados/74749",
      "nome": "MAURO LOPES",
      "siglaPartido": "PMDB",
      "uriPartido": "https://dadosabertos.camara.leg.br/api/v2/partidos/36800",
      "siglaUf": "MG",
      "idLegislatura": 55,
      "urlFoto": "http://www.camara.leg.br/internet/deputado/bandep/74749.jpg"
    },
    {
      "id": 141507,
      "uri": "https://dadosabertos.camara.leg.br/api/v2/deputados/141507",
      "nome": "MAURO MARIANI",
      "siglaPartido": "PMDB",
      "uriPartido": "https://dadosabertos.camara.leg.br/api/v2/partidos/36800",
      "siglaUf": "SC",
      "idLegislatura": 55,
      "urlFoto": "http://www.camara.leg.br/internet/deputado/bandep/141507.jpg"
    },
    {
      "id": 124411,
      "uri": "https://dadosabertos.camara.leg.br/api/v2/deputados/124411",
      "nome": "MAURO PEREIRA",
      "siglaPartido": "PMDB",
      "uriPartido": "https://dadosabertos.camara.leg.br/api/v2/partidos/36800",
      "siglaUf": "RS",
      "idLegislatura": 55,
      "urlFoto": "http://www.camara.leg.br/internet/deputado/bandep/124411.jpg"
    },
    {
      "id": 178827,
      "uri": "https://dadosabertos.camara.leg.br/api/v2/deputados/178827",
      "nome": "MAX FILHO",
      "siglaPartido": "PSDB",
      "uriPartido": "https://dadosabertos.camara.leg.br/api/v2/partidos/36835",
      "siglaUf": "ES",
      "idLegislatura": 55,
      "urlFoto": "http://www.camara.leg.br/internet/deputado/bandep/178827.jpg"
    },
    {
      "id": 74428,
      "uri": "https://dadosabertos.camara.leg.br/api/v2/deputados/74428",
      "nome": "MENDONÇA FILHO",
      "siglaPartido": "DEM",
      "uriPartido": "https://dadosabertos.camara.leg.br/api/v2/partidos/36769",
      "siglaUf": "PE",
      "idLegislatura": 55,
      "urlFoto": "http://www.camara.leg.br/internet/deputado/bandep/74428.jpg"
    },
    {
      "id": 188097,
      "uri": "https://dadosabertos.camara.leg.br/api/v2/deputados/188097",
      "nome": "MERLONG SOLANO",
      "siglaPartido": "PT",
      "uriPartido": "https://dadosabertos.camara.leg.br/api/v2/partidos/36844",
      "siglaUf": "PI",
      "idLegislatura": 55,
      "urlFoto": "http://www.camara.leg.br/internet/deputado/bandep/188097.jpg"
    },
    {
      "id": 141509,
      "uri": "https://dadosabertos.camara.leg.br/api/v2/deputados/141509",
      "nome": "MIGUEL CORRÊA",
      "siglaPartido": "PT",
      "uriPartido": "https://dadosabertos.camara.leg.br/api/v2/partidos/36844",
      "siglaUf": "MG",
      "idLegislatura": 55,
      "urlFoto": "http://www.camara.leg.br/internet/deputado/bandep/141509.jpg"
    },
    {
      "id": 178984,
      "uri": "https://dadosabertos.camara.leg.br/api/v2/deputados/178984",
      "nome": "MIGUEL HADDAD",
      "siglaPartido": "PSDB",
      "uriPartido": "https://dadosabertos.camara.leg.br/api/v2/partidos/36835",
      "siglaUf": "SP",
      "idLegislatura": 55,
      "urlFoto": "http://www.camara.leg.br/internet/deputado/bandep/178984.jpg"
    }
  ],
  "links": [
    {
      "rel": "self",
      "href": "https://dadosabertos.camara.leg.br/api/v2/deputados?idLegislatura=55&itens=100&ordem=ASC&ordenarPor=nome&pagina=4"
    },
    {
      "rel": "next",
      "href": "https://dadosabertos.camara.leg.br/api/v2/deputados/?idLegislatura=55&pagina=5&itens=100"
    },
    {
      "rel": "first",
      "href": "https://dadosabertos.camara.leg.br/api/v2/deputados/?idLegislatura=55&pagina=1&itens=100"
    },
    {
      "rel": "last",
      "href": "https://dadosabertos.camara.leg.br/api/v2/deputados/?idLegislatura=55&pagina=7&itens=100"
    },
    {
      "rel": "previous",
      "href": "https://dadosabertos.camara.leg.br/api/v2/deputados/?idLegislatura=55&pagina=3&itens=100"
    }
  ]
}
